COPYING
COPYING.LESSER
MANIFEST.in
requirements.setup.txt
requirements.test.txt
requirements.txt
setup.py
Boost/Source.py
Boost/__init__.py
Boost/__version__.py
pyboost.egg-info/PKG-INFO
pyboost.egg-info/SOURCES.txt
pyboost.egg-info/dependency_links.txt
pyboost.egg-info/requires.txt
pyboost.egg-info/top_level.txt
test/conftest.py
test/test_Source.py