Metadata-Version: 1.1
Name: pyboost
Version: 0.1.dev18
Summary: C++Boost as a Python package
Home-page: https://github.com/zimmermanncode/pyboost
Author: Stefan Zimmermann
Author-email: user@zimmermann.co
License: LGPLv3
Keywords: pyboost,boost,python3,packaging,c++,cpp,cxx,cplusplus,libraries,libs,library,lib,boostpython
Platform: UNKNOWN
Classifier: Development Status :: 3 - Alpha
Classifier: Intended Audience :: Developers
Classifier: License :: OSI Approved :: GNU Library or Lesser General Public License (LGPL)
Classifier: Operating System :: OS Independent
Classifier: Programming Language :: Python
Classifier: Programming Language :: Python :: 2
Classifier: Programming Language :: Python :: 2.7
Classifier: Programming Language :: Python :: 3
Classifier: Programming Language :: Python :: 3.3
Classifier: Programming Language :: Python :: 3.4
Classifier: Programming Language :: Python :: 3.5
Classifier: Programming Language :: Python :: 3.6
Classifier: Topic :: Software Development
Classifier: Topic :: Utilities
